{
    "workoutTitle": "Chest and Triceps",
    "users": [
      
    ],
    "exercises": [
      {
        "exerciseName": "Barbell Bench Press",
        "targetSets": 4,
        "targetSetReps": [
          15,
          12,
          10,
          8
        ]
      },
      {
        "exerciseName": "Cable Fly",
        "targetSets": 4,
        "targetSetReps": [
          15,
          15,
          15,
          15
        ]
      }
    ]
  }


  [
    {
        "schedule": [
            {
                "date": "2023-02-11T13:41:00.000+00:00",
                "workoutID": "63d33ecbfdfb5019768707cc",
                "workoutTitle": "Test ID Workout",
                "completed": false
            },
            {
                "date": "2023-02-12T13:41:00.000+00:00",
                "workoutID": "63d85ef2df729d266e0948b6",
                "workoutTitle": "New Test Workout",
                "completed": false
            },
            {
                "date": "2023-02-13T13:41:00.000+00:00",
                "workoutID": "63dc67d636f92e5276e8b676",
                "workoutTitle": "Thursday Test Workout",
                "completed": false
            },
            {
                "date": "2023-02-14T13:41:00.000+00:00",
                "workoutID": "",
                "workoutTitle": "",
                "completed": false
            },
            {
                "date": "2023-02-15T13:41:00.000+00:00",
                "workoutID": "",
                "workoutTitle": "",
                "completed": false
            }
        ],
        "_id": "63e83bafe9680ad5b25d4985",
        "user": "3r4xMR0NHFgbEWEKTTMfqWw0tDG3"
    }
]


  //exercise structure


    {
        "secondaryMuscleGroups": [
            "triceps",
            "biceps",
            "shoulders"
        ],
        "_id": "63894e8e183aff5cb54f2208",
        "exerciseName": "Barbell Bench Press",
        "primaryMuscleGroups": "Chest"
    }